gvec_to_python/GVEC_functions.py
gvec_to_python/Makefile
gvec_to_python/__init__.py
gvec_to_python/main.py
gvec_to_python/version.py
gvec_to_python/base/__init__.py
gvec_to_python/base/base.py
gvec_to_python/base/fbase.py
gvec_to_python/base/make_base.py
gvec_to_python/base/sbase.py
gvec_to_python/console/__init__.py
gvec_to_python/console/compile.py
gvec_to_python/equilibrium/__init__.py
gvec_to_python/equilibrium/profiles.py
gvec_to_python/geometry/__init__.py
gvec_to_python/geometry/domain.py
gvec_to_python/hylife/__init__.py
gvec_to_python/hylife/utilities_FEEC/__init__.py
gvec_to_python/hylife/utilities_FEEC/bsplines.py
gvec_to_python/hylife/utilities_FEEC/bsplines_kernels.py
gvec_to_python/hylife/utilities_FEEC/spline_space.py
gvec_to_python/hylife/utilities_FEEC/basics/__init__.py
gvec_to_python/hylife/utilities_FEEC/basics/spline_evaluation_1d.py
gvec_to_python/hylife/utilities_FEEC/derivatives/__init__.py
gvec_to_python/hylife/utilities_FEEC/derivatives/derivatives.py
gvec_to_python/reader/__init__.py
gvec_to_python/reader/gvec_reader.py
gvec_to_python/testcases/__init__.py
gvec_to_python/testcases/circ_tok/CIRC_TOK_State_0000_00010000.dat
gvec_to_python/testcases/circ_tok/parameter.ini
gvec_to_python/testcases/ellipstell/newBC_E1D6_M6N6/GVEC_ELLIPSTELL_E1D6_M6N6_State_0000_00200000.dat
gvec_to_python/testcases/ellipstell/newBC_E1D6_M6N6/parameter.ini
gvec_to_python/testcases/ellipstell/newBC_E4D6_M6N6/GVEC_ELLIPSTELL_E4D6_M6N6_State_0001_00200000.dat
gvec_to_python/testcases/ellipstell/newBC_E4D6_M6N6/parameter.ini
gvec_to_python/testcases/ellipstell_v2/newBC_E1D6_M6N6/GVEC_ELLIPSTELL_V2_State_0000_00200000.dat
gvec_to_python/testcases/ellipstell_v2/newBC_E1D6_M6N6/parameter.ini
gvec_to_python/testcases/ellipstell_v2/newBC_E4D6_M6N6/GVEC_ELLIPSTELL_V2_State_0000_00200000.dat
gvec_to_python/testcases/ellipstell_v2/newBC_E4D6_M6N6/parameter.ini
gvec_to_python/testcases/ellipstell_v2/oldBC_E40D5M6N6/GVEC_ELLIPSTELL_V2_State_0000_00200000.dat
gvec_to_python-1.2.2.dist-info/LICENSE
gvec_to_python-1.2.2.dist-info/METADATA
gvec_to_python-1.2.2.dist-info/WHEEL
gvec_to_python-1.2.2.dist-info/entry_points.txt
gvec_to_python-1.2.2.dist-info/top_level.txt
gvec_to_python-1.2.2.dist-info/RECORD
