Metadata-Version: 2.1
Name: gvec-to-python
Version: 1.2.2
Summary: Parse GVEC output in Python
Author: Tin Kei Cheng, Florian Hindenlang, Stefan Possanner
Author-email: stefan.possanner@ipp.mpg.de, florian.hindenlang@ipp.mpg.de
License: Copyright 2021 (c) T.K. Cheng, F. Hindenlang, S. Possanner | Max Planck Institute for Plasma Physics
Project-URL: repository, https://gitlab.mpcdf.mpg.de/gvec-group/gvec_to_python
Project-URL: Bug Tracker, https://gitlab.mpcdf.mpg.de/gvec-group/gvec_to_python/-/issues
Keywords: plasma physics,fusion,numerical modeling,mhd equilibrium
Classifier: Programming Language :: Python :: 3
Requires-Python: >=3.7
License-File: LICENSE
Requires-Dist: matplotlib
Requires-Dist: numpy
Requires-Dist: pandas
Requires-Dist: pyccel
Requires-Dist: scipy
Requires-Dist: tqdm
Requires-Dist: vtk
Requires-Dist: argcomplete
